carnetordre/__init__.py
carnetordre/col.py
CARNETORDREKB-1.0.0.dist-info/LICENSE
CARNETORDREKB-1.0.0.dist-info/METADATA
CARNETORDREKB-1.0.0.dist-info/WHEEL
CARNETORDREKB-1.0.0.dist-info/entry_points.txt
CARNETORDREKB-1.0.0.dist-info/top_level.txt
CARNETORDREKB-1.0.0.dist-info/RECORD
