Metadata-Version: 2.1
Name: CARNETORDREKB
Version: 1.0.0
Summary: Algorithm for finance
Home-page: UNKNOWN
License: MIT
Platform: UNKNOWN
